snowbim/__init__.py
snowbim/__main__.py
snowbim/snowbim.py
snowbim/engines/__init__.py
snowbim/engines/bimengine.py
snowbim/engines/snowengine.py
snowbim/utilities/__init__.py
snowbim/utilities/common.py
snowbim-1.0.12.dist-info/LICENSE
snowbim-1.0.12.dist-info/METADATA
snowbim-1.0.12.dist-info/WHEEL
snowbim-1.0.12.dist-info/entry_points.txt
snowbim-1.0.12.dist-info/top_level.txt
snowbim-1.0.12.dist-info/RECORD
