Metadata-Version: 2.1
Name: snowbim
Version: 1.0.12
Summary: A package to refresh power bi model .bim file
Home-page: https://github.com/datnguye/snowbim
Author: datnguye
Author-email: datnguyen.it09@gmail.com
License: MIT
Platform: UNKNOWN
Requires-Python: >=3.7.5
Requires-Dist: pyyaml (==5.4.1)
Requires-Dist: snowflake-connector-python (==2.3.6)
Requires-Dist: snowflake-connector-python[pandas]
